{"data":{"_id":3000,"properties":{"rootFileSystemObjectId":{"name":"rootFileSystemObjectId","kind":"scalar","getter":false,"setter":false,"type":"string","array":false,"runtimeType":"string"}},"primaryKeys":[],"filters":{},"hooks":{"beforeCreate":["createFileSystem"],"beforeDelete":["deleteFileSystem"]},"indexes":[],"uniques":[],"className":"FileSystemEntity","path":"./dist/src/entities/FileSystem.entity.js","name":"FileSystemEntity","abstract":false,"internal":true,"constructorParams":[],"toJsonParams":[],"extends":"UniqueEntity","useCache":true,"collection":"file_system_entity"},"origin":"./dist/src/entities/FileSystem.entity.js","hash":"026a4741e81d144b39895fdc6b0c7ec0","version":"6.5.8"}
